gotipy/__init__.py
gotipy/gotipy.py
gotipy-0.2.2.dist-info/LICENSE
gotipy-0.2.2.dist-info/WHEEL
gotipy-0.2.2.dist-info/METADATA
gotipy-0.2.2.dist-info/RECORD
