Metadata-Version: 2.1
Name: gotipy
Version: 0.2.2
Summary: A simple Python wrapper for Gotify
License: MIT
Author: Mohammad Alyetama
Author-email: malyetama@pm.me
Requires-Python: >=3.6,<4.0
Classifier: License :: OSI Approved :: MIT License
Classifier: Programming Language :: Python :: 3
Classifier: Programming Language :: Python :: 3.10
Classifier: Programming Language :: Python :: 3.6
Classifier: Programming Language :: Python :: 3.7
Classifier: Programming Language :: Python :: 3.8
Classifier: Programming Language :: Python :: 3.9
Requires-Dist: requests (>=2.28.1,<3.0.0)
